{"20": {"slices": ["q20_0.png"], "rects": [[2, 0, 166.3, 673.4, 81.7, 418.1]]}, "21": {"slices": ["q21_0.png"], "rects": [[2, 0, 675.4, 1103.1, 81.7, 418.1]]}, "22": {"slices": ["q22_0.png"], "rects": [[2, 1, 166.3, 692.8, 422.9, 761.0]]}, "23": {"slices": ["q23_0.png"], "rects": [[2, 1, 694.8, 1107.9, 422.9, 761.0]]}, "24": {"slices": ["q24_0.png"], "rects": [[3, 0, 165.8, 658.0, 81.7, 413.0]]}, "31": {"slices": ["q31_0.png"], "rects": [[4, 1, 765.6, 1107.9, 422.9, 761.0]]}, "32": {"slices": ["q32_0.png"], "rects": [[5, 0, 166.3, 467.5, 91.1, 418.0]]}, "33": {"slices": ["q33_0.png"], "rects": [[5, 0, 469.5, 757.4, 91.1, 418.0]]}, "34": {"slices": ["q34_0.png"], "rects": [[5, 0, 759.4, 1103.1, 91.1, 418.0]]}, "35": {"slices": ["q35_0.png"], "rects": [[5, 1, 171.3, 654.8, 422.9, 758.8]]}, "36": {"slices": ["q36_0.png"], "rects": [[5, 1, 656.8, 1107.9, 422.9, 758.8]]}, "37": {"slices": ["q37_0.png"], "rects": [[6, 0, 166.3, 812.0, 81.7, 417.6]]}, "38": {"slices": ["q38_0.png"], "rects": [[6, 0, 814.0, 1103.1, 81.7, 417.6]]}, "39": {"slices": ["q39_0.png"], "rects": [[6, 1, 166.3, 531.9, 422.9, 761.0]]}, "40": {"slices": ["q40_0.png"], "rects": [[6, 1, 533.9, 1107.9, 422.9, 761.0]]}}